playwright_server_custom/__init__.py
playwright_server_custom/server.py
playwright_server_custom/tools.py
playwright_server_custom-0.1.4.dist-info/METADATA
playwright_server_custom-0.1.4.dist-info/WHEEL
playwright_server_custom-0.1.4.dist-info/entry_points.txt
playwright_server_custom-0.1.4.dist-info/RECORD
