Metadata-Version: 2.4
Name: playwright-server-custom
Version: 0.1.4
Summary: Playwright MCP server
Author-email: Saubhagya Dwitiya <saubhagya.carvia@gmail.com>
Requires-Python: >=3.11
Requires-Dist: mcp>=1.9.0
Requires-Dist: playwright>=1.52.0
